PyCustom/__init__.py
PyCustom/ppscore.py
PyCustom-0.0.4.dist-info/LICENSE
PyCustom-0.0.4.dist-info/METADATA
PyCustom-0.0.4.dist-info/WHEEL
PyCustom-0.0.4.dist-info/top_level.txt
PyCustom-0.0.4.dist-info/RECORD
